{"_type":"export","__export_format":4,"__export_date":"2024-02-04T03:48:37.506Z","__export_source":"insomnia.desktop.app:v8.6.0","resources":[{"_id":"req_7ad37b84f6ba444f8650bff03b8c952c","parentId":"wrk_4897dfd5ad4a4a54a0c544985b3b410c","modified":1706994871527,"created":1706992476757,"url":"http://localhost:3000/api/user","name":"latest filter","description":"","method":"GET","body":{},"parameters":[],"headers":[{"name":"User-Agent","value":"insomnia/8.6.0"}],"authentication":{},"metaSortKey":-1706992476757,"isPrivate":false,"pathParameters":[],"settingStoreCookies":true,"settingSendCookies":true,"settingDisableRenderRequestBody":false,"settingEncodeUrl":true,"settingRebuildPath":true,"settingFollowRedirects":"global","_type":"request"},{"_id":"wrk_4897dfd5ad4a4a54a0c544985b3b410c","parentId":null,"modified":1706996993442,"created":1706996993442,"name":"Insomnia Documenter Demo","description":"","scope":"collection","_type":"workspace"},{"_id":"env_554bf5e23d714e83afcb75b21ea3d9f3","parentId":"wrk_4897dfd5ad4a4a54a0c544985b3b410c","modified":1568821879007,"created":1568819138060,"name":"Base Environment","data":{"baseUrl":"http://localhost:3000","postUuid":44},"dataPropertyOrder":{"&":["baseUrl","postUuid"]},"color":null,"isPrivate":false,"metaSortKey":1568819138060,"_type":"environment"},{"_id":"jar_5bc97ccb1be24d8a8555e00559ff70c8","parentId":"wrk_4897dfd5ad4a4a54a0c544985b3b410c","modified":1568819294484,"created":1568819138109,"name":"Default Jar","cookies":[{"domain":"httpbin.org","httpOnly":false,"id":"dadfe2eb-a370-4a3b-bbbb-99cffaeb324b","key":"hello","path":"/cookies","secure":false,"value":"world"}],"_type":"cookie_jar"},{"_id":"env_fa0c3e533db44ed7b2db62ec2e3b04c2","parentId":"env_554bf5e23d714e83afcb75b21ea3d9f3","modified":1568822635086,"created":1568819189892,"name":"Production","data":{"baseUrl":"https://httpbin.org","token":"eyJhbGciOiJIUzI1NiIsInR5cCI6IkpXVCJ9.eyJ1c2VybmFtZSI6ImpvZSIsInBhc3N3b3JkIjoiam9lMTIzIn0.gP1gYgGlbqW13egDw1-_u-erKep24kFTj8Ra2yYhi_0"},"dataPropertyOrder":{"&":["baseUrl","token"]},"color":"#7d69cb","isPrivate":false,"metaSortKey":1568819189892,"_type":"environment"},{"_id":"env_27053d1df31c4fac967fed1588a8d5cd","parentId":"env_554bf5e23d714e83afcb75b21ea3d9f3","modified":1568822647051,"created":1568819210935,"name":"Development","data":{"baseUrl":"http://localhost:3000","token":"bearer_token"},"dataPropertyOrder":{"&":["baseUrl","token"]},"color":"#ec7600","isPrivate":false,"metaSortKey":1568819210935,"_type":"environment"}]}